[{"id":444088,"id_state":1684,"name":"Agua Caliente"},{"id":444164,"id_state":1684,"name":"Amatillo"},{"id":444242,"id_state":1684,"name":"Bacadilla"},{"id":444251,"id_state":1684,"name":"Baltimore"},{"id":444253,"id_state":1684,"name":"Bananera"},{"id":444281,"id_state":1684,"name":"Barra San Marcos"},{"id":444329,"id_state":1684,"name":"Blue Creek"},{"id":444331,"id_state":1684,"name":"Boca Ancha"},{"id":444385,"id_state":1684,"name":"Buenos Aires"},{"id":444408,"id_state":1684,"name":"Cacao"},{"id":444602,"id_state":1684,"name":"Castillo de San Felipe"},{"id":444658,"id_state":1684,"name":"Cerro Blanco"},{"id":445777,"id_state":1684,"name":"El Estor"},{"id":446148,"id_state":1684,"name":"El Rico"},{"id":446362,"id_state":1684,"name":"Entre Ríos"},{"id":446535,"id_state":1684,"name":"Fronteras"},{"id":446565,"id_state":1684,"name":"Gran Cañón"},{"id":446576,"id_state":1684,"name":"Guacamayo"},{"id":446761,"id_state":1684,"name":"Izabal"},{"id":446912,"id_state":1684,"name":"La Barra"},{"id":447375,"id_state":1684,"name":"Las Escobas"},{"id":447584,"id_state":1684,"name":"La Viña"},{"id":447615,"id_state":1684,"name":"Lívingston"},{"id":447711,"id_state":1684,"name":"Los Amates"},{"id":448004,"id_state":1684,"name":"Manguito"},{"id":448032,"id_state":1684,"name":"Mariscos"},{"id":448091,"id_state":1684,"name":"Mixco"},{"id":448150,"id_state":1684,"name":"Morales"},{"id":448802,"id_state":1684,"name":"Plan Grande Tatín"},{"id":448927,"id_state":1684,"name":"Puerto Barrios"},{"id":448935,"id_state":1684,"name":"Puerto de Santo Tomás"},{"id":448940,"id_state":1684,"name":"Puerto Santo Tomás de Castilla"},{"id":448956,"id_state":1684,"name":"Punta Palma"},{"id":449028,"id_state":1684,"name":"Quiriguá"},{"id":449118,"id_state":1684,"name":"Río Blanco"},{"id":449122,"id_state":1684,"name":"Río Bonito"},{"id":449187,"id_state":1684,"name":"Rubelpec"},{"id":449409,"id_state":1684,"name":"San Felipe"},{"id":449970,"id_state":1684,"name":"Santo Tomás"},{"id":449973,"id_state":1684,"name":"Santo Tomás de Castilla"},{"id":450079,"id_state":1684,"name":"Sejá"}]
