[{"id":161494,"id_state":930,"name":"Aamdal"},{"id":161991,"id_state":930,"name":"Åseral"},{"id":163164,"id_state":930,"name":"Christiansand"},{"id":163680,"id_state":930,"name":"Engeland"},{"id":164175,"id_state":930,"name":"Flekkefjord"},{"id":164863,"id_state":930,"name":"Grimestad"},{"id":165107,"id_state":930,"name":"Hægebostad"},{"id":166847,"id_state":930,"name":"Kjevik"},{"id":167121,"id_state":930,"name":"Korshamn"},{"id":167199,"id_state":930,"name":"Kristiansand"},{"id":167201,"id_state":930,"name":"Kristiansand Sør"},{"id":167406,"id_state":930,"name":"Kvinesdal"},{"id":168174,"id_state":930,"name":"Lyngdal"},{"id":168265,"id_state":930,"name":"Mandal"},{"id":172559,"id_state":930,"name":"Tangvall"},{"id":173539,"id_state":930,"name":"Vennesla"}]
