[{"id":436605,"id_state":1631,"name":"Alto Verá"},{"id":436622,"id_state":1631,"name":"Arquitecto Tomás Romero Pereira"},{"id":436629,"id_state":1631,"name":"Asseradero"},{"id":436653,"id_state":1631,"name":"Bella Vista"},{"id":436654,"id_state":1631,"name":"Bella Vista de Alto Paraná"},{"id":436691,"id_state":1631,"name":"Cambyretá"},{"id":436719,"id_state":1631,"name":"Capitán Meza"},{"id":436720,"id_state":1631,"name":"Capitán Miranda"},{"id":436733,"id_state":1631,"name":"Carlos Antonio López"},{"id":436736,"id_state":1631,"name":"Carmen del Paraná"},{"id":436791,"id_state":1631,"name":"Colonia Bella Vista"},{"id":436838,"id_state":1631,"name":"Colonia Fram"},{"id":436864,"id_state":1631,"name":"Colonia Hohenau"},{"id":437040,"id_state":1631,"name":"Coronel Bogado"},{"id":437042,"id_state":1631,"name":"Coronel Jose F. Bogado"},{"id":437093,"id_state":1631,"name":"Edelira"},{"id":437102,"id_state":1631,"name":"Encarnación"},{"id":437656,"id_state":1631,"name":"Fram"},{"id":437671,"id_state":1631,"name":"General Artigas"},{"id":437703,"id_state":1631,"name":"Hohenau"},{"id":437740,"id_state":1631,"name":"Itapúa Poty"},{"id":437760,"id_state":1631,"name":"José Potrero"},{"id":437784,"id_state":1631,"name":"La Paz"},{"id":437874,"id_state":1631,"name":"Naranjito"},{"id":437878,"id_state":1631,"name":"Natalio"},{"id":437899,"id_state":1631,"name":"Obligado"},{"id":437954,"id_state":1631,"name":"Pirapo"},{"id":437955,"id_state":1631,"name":"Piratey"},{"id":438369,"id_state":1631,"name":"Santa María"},{"id":438468,"id_state":1631,"name":"Trinidad"},{"id":438519,"id_state":1631,"name":"Yatairy"}]
