[{"id":67377,"id_state":724,"name":"Bühler"},{"id":67378,"id_state":724,"name":"Gais"},{"id":67379,"id_state":724,"name":"Heiden"},{"id":67380,"id_state":724,"name":"Herisau"},{"id":67381,"id_state":724,"name":"Hundwil"},{"id":67382,"id_state":724,"name":"Rehetobel"},{"id":67383,"id_state":724,"name":"Schönengrund"},{"id":67384,"id_state":724,"name":"Schwellbrunn"},{"id":67385,"id_state":724,"name":"Speicher"},{"id":67386,"id_state":724,"name":"Trogen"},{"id":67387,"id_state":724,"name":"Urnäsch"},{"id":67388,"id_state":724,"name":"Waldstatt"},{"id":67389,"id_state":724,"name":"Walzenhausen"},{"id":67390,"id_state":724,"name":"Zürchersmühle"}]
