[{"id":778289,"id_state":2062,"name":"Aalst"},{"id":778293,"id_state":2062,"name":"Aalten"},{"id":778295,"id_state":2062,"name":"Aam"},{"id":778307,"id_state":2062,"name":"Aard"},{"id":778312,"id_state":2062,"name":"Aardt"},{"id":778347,"id_state":2062,"name":"Achter de Vree"},{"id":778352,"id_state":2062,"name":"Achterdrempt"},{"id":778356,"id_state":2062,"name":"Achterhoek"},{"id":778371,"id_state":2062,"name":"Achterstehoek"},{"id":778376,"id_state":2062,"name":"Achterwehl"},{"id":778388,"id_state":2062,"name":"Acquoy"},{"id":778427,"id_state":2062,"name":"Alfen"},{"id":778465,"id_state":2062,"name":"Alverna"},{"id":778529,"id_state":2062,"name":"Apeldoorn"},{"id":778551,"id_state":2062,"name":"Arnheim"},{"id":778552,"id_state":2062,"name":"Arnhem"},{"id":778642,"id_state":2062,"name":"Babberich"},{"id":778709,"id_state":2062,"name":"Barneveld"},{"id":778739,"id_state":2062,"name":"Beek"},{"id":778800,"id_state":2062,"name":"Bemmel"},{"id":778819,"id_state":2062,"name":"Bennekom"},{"id":778915,"id_state":2062,"name":"Beuningen"},{"id":779125,"id_state":2062,"name":"Borkulo"},{"id":779219,"id_state":2062,"name":"Brakel"},{"id":779500,"id_state":2062,"name":"Culemborg"},{"id":779502,"id_state":2062,"name":"Culenborg"},{"id":779677,"id_state":2062,"name":"De Heurne"},{"id":779835,"id_state":2062,"name":"De Middel Buurt"},{"id":780066,"id_state":2062,"name":"Dieren"},{"id":780104,"id_state":2062,"name":"Dinxperlo"},{"id":780118,"id_state":2062,"name":"Doesburg"},{"id":780121,"id_state":2062,"name":"Doetinchem"},{"id":780241,"id_state":2062,"name":"Druten"},{"id":780256,"id_state":2062,"name":"Duiven"},{"id":780299,"id_state":2062,"name":"Ede"},{"id":780337,"id_state":2062,"name":"Eerbeek"},{"id":780425,"id_state":2062,"name":"Elden"},{"id":780442,"id_state":2062,"name":"Ellecom"},{"id":780534,"id_state":2062,"name":"Ermelo"},{"id":780745,"id_state":2062,"name":"Geldermalsen"},{"id":780951,"id_state":2062,"name":"Groenendaal"},{"id":780966,"id_state":2062,"name":"Groesbeek"},{"id":781159,"id_state":2062,"name":"Harderwijk"},{"id":781210,"id_state":2062,"name":"Hattem"},{"id":781260,"id_state":2062,"name":"Heerde"},{"id":781416,"id_state":2062,"name":"Hengelo"},{"id":781854,"id_state":2062,"name":"Horssen"},{"id":781905,"id_state":2062,"name":"Huissen"},{"id":782219,"id_state":2062,"name":"Kesteren"},{"id":782268,"id_state":2062,"name":"Klarenbeek"},{"id":782280,"id_state":2062,"name":"Klein Baal"},{"id":782771,"id_state":2062,"name":"Leeuwen"},{"id":782813,"id_state":2062,"name":"Lent"},{"id":782836,"id_state":2062,"name":"Leuvenheim"},{"id":782853,"id_state":2062,"name":"Lichtenvoorde"},{"id":782921,"id_state":2062,"name":"Lochem"},{"id":783092,"id_state":2062,"name":"Malden"},{"id":783494,"id_state":2062,"name":"Neede"},{"id":783498,"id_state":2062,"name":"Neerbosch"},{"id":783719,"id_state":2062,"name":"Nijkerk"},{"id":783725,"id_state":2062,"name":"Nijmegen"},{"id":783726,"id_state":2062,"name":"Nijmeyen"},{"id":783736,"id_state":2062,"name":"Nimègue"},{"id":783738,"id_state":2062,"name":"Nimwegen"},{"id":783857,"id_state":2062,"name":"Nymegen"},{"id":783906,"id_state":2062,"name":"Oldebroek"},{"id":784040,"id_state":2062,"name":"Oosterhout"},{"id":784819,"id_state":2062,"name":"Rozendaal"},{"id":784963,"id_state":2062,"name":"Scherpenzeel"},{"id":785096,"id_state":2062,"name":"s-Heerenberg"},{"id":785332,"id_state":2062,"name":"Spijk"},{"id":785455,"id_state":2062,"name":"Stokkum"},{"id":785708,"id_state":2062,"name":"Tiel"},{"id":785768,"id_state":2062,"name":"t Loo"},{"id":785779,"id_state":2062,"name":"Toldijk"},{"id":785781,"id_state":2062,"name":"Tolkamer"},{"id":785829,"id_state":2062,"name":"t Ruurlose Broek"},{"id":785886,"id_state":2062,"name":"Twello"},{"id":785944,"id_state":2062,"name":"Ulft"},{"id":785978,"id_state":2062,"name":"Vaassen"},{"id":786091,"id_state":2062,"name":"Velp"},{"id":786099,"id_state":2062,"name":"Veluwe"},{"id":786276,"id_state":2062,"name":"Voorthuizen"},{"id":786394,"id_state":2062,"name":"Wageningen"},{"id":786608,"id_state":2062,"name":"Westervoort"},{"id":786658,"id_state":2062,"name":"Wezep"},{"id":786666,"id_state":2062,"name":"Wieken"},{"id":786692,"id_state":2062,"name":"Wijchen"},{"id":786788,"id_state":2062,"name":"Winterswijk"},{"id":786915,"id_state":2062,"name":"Zaltbommel"},{"id":786991,"id_state":2062,"name":"Zevenaar"},{"id":787111,"id_state":2062,"name":"Zuilichem"},{"id":787120,"id_state":2062,"name":"Zutfen"},{"id":787122,"id_state":2062,"name":"Zutphen"},{"id":787176,"id_state":2062,"name":"Zwolle"}]
