[{"id":69375,"id_state":755,"name":"Água d Alte"},{"id":69433,"id_state":755,"name":"Aguiar"},{"id":69482,"id_state":755,"name":"Alandroal"},{"id":69516,"id_state":755,"name":"Alcáçovas"},{"id":69595,"id_state":755,"name":"Aldeia"},{"id":69624,"id_state":755,"name":"Aldeia da Nora"},{"id":69734,"id_state":755,"name":"Aldeias"},{"id":69967,"id_state":755,"name":"Alqueva"},{"id":70471,"id_state":755,"name":"Arneiros de Baixo"},{"id":70499,"id_state":755,"name":"Arrabis"},{"id":70504,"id_state":755,"name":"Arraiolos"},{"id":70728,"id_state":755,"name":"Azaruja"},{"id":71105,"id_state":755,"name":"Barro Branco"},{"id":71260,"id_state":755,"name":"Bencatel"},{"id":71364,"id_state":755,"name":"Boa Fé"},{"id":71499,"id_state":755,"name":"Borba"},{"id":71505,"id_state":755,"name":"Borda"},{"id":71804,"id_state":755,"name":"Cabeça de Carneiro"},{"id":71898,"id_state":755,"name":"Cabrela"},{"id":72137,"id_state":755,"name":"Campinho"},{"id":72721,"id_state":755,"name":"Casa Branca"},{"id":74111,"id_state":755,"name":"Cortiçadas"},{"id":74112,"id_state":755,"name":"Cortiçadas do Lavre"},{"id":74139,"id_state":755,"name":"Corujeira"},{"id":74663,"id_state":755,"name":"Ébora"},{"id":74870,"id_state":755,"name":"Escoural"},{"id":75058,"id_state":755,"name":"Estremoz"},{"id":75068,"id_state":755,"name":"Évora"},{"id":75070,"id_state":755,"name":"Évora Monte"},{"id":75418,"id_state":755,"name":"Figueiras de Cima"},{"id":75765,"id_state":755,"name":"Foros do Queimado"},{"id":76596,"id_state":755,"name":"Igrejinha"},{"id":77072,"id_state":755,"name":"Lavre"},{"id":78302,"id_state":755,"name":"Monsaraz"},{"id":78383,"id_state":755,"name":"Monte da Azinheira"},{"id":78394,"id_state":755,"name":"Monte da Chaminé"},{"id":78687,"id_state":755,"name":"Montemor-o-Novo"},{"id":78773,"id_state":755,"name":"Monte Trigo"},{"id":78811,"id_state":755,"name":"Mora"},{"id":78942,"id_state":755,"name":"Mourão"},{"id":79212,"id_state":755,"name":"Nossa Senhora de Machede"},{"id":79341,"id_state":755,"name":"Orada"},{"id":79582,"id_state":755,"name":"Paião"},{"id":79951,"id_state":755,"name":"Pavia"},{"id":80804,"id_state":755,"name":"Portel"},{"id":81802,"id_state":755,"name":"Redondo"},{"id":81857,"id_state":755,"name":"Reguengo"},{"id":81875,"id_state":755,"name":"Reguengos"},{"id":81876,"id_state":755,"name":"Reguengos de Monsaraz"},{"id":82177,"id_state":755,"name":"Rio de Moinhos"},{"id":83264,"id_state":755,"name":"São Manços"},{"id":83270,"id_state":755,"name":"São Marcos do Campo"},{"id":83348,"id_state":755,"name":"São Miguel de Machede"},{"id":83419,"id_state":755,"name":"São Pedro do Corval"},{"id":83994,"id_state":755,"name":"Silveiras"},{"id":85618,"id_state":755,"name":"Veiros"},{"id":85634,"id_state":755,"name":"Venda"},{"id":85692,"id_state":755,"name":"Vendas Novas"},{"id":85766,"id_state":755,"name":"Viana do Alentejo"},{"id":86315,"id_state":755,"name":"Vila Viçosa"},{"id":86365,"id_state":755,"name":"Vimieiro"}]
