[{"id":573497,"id_state":1848,"name":"Abasacapán"},{"id":573498,"id_state":1848,"name":"Abati"},{"id":573517,"id_state":1848,"name":"Aceitico"},{"id":573553,"id_state":1848,"name":"Agua Blanca"},{"id":573571,"id_state":1848,"name":"Agua Blanquita"},{"id":573603,"id_state":1848,"name":"Agua Clara"},{"id":573676,"id_state":1848,"name":"Agua Linda"},{"id":573685,"id_state":1848,"name":"Agua Negra"},{"id":573691,"id_state":1848,"name":"Agua Nieve"},{"id":573698,"id_state":1848,"name":"Agua Salada"},{"id":573722,"id_state":1848,"name":"Agua Verde"},{"id":573733,"id_state":1848,"name":"Agüerito"},{"id":573743,"id_state":1848,"name":"Ají"},{"id":573778,"id_state":1848,"name":"Algarroba"},{"id":573801,"id_state":1848,"name":"Alma"},{"id":573802,"id_state":1848,"name":"Almacén"},{"id":573803,"id_state":1848,"name":"Almacenes"},{"id":573811,"id_state":1848,"name":"Altagracia"},{"id":573821,"id_state":1848,"name":"Altamira"},{"id":573917,"id_state":1848,"name":"Amanauo"},{"id":573921,"id_state":1848,"name":"Aman-tepuí"},{"id":573922,"id_state":1848,"name":"Amantepuy"},{"id":573927,"id_state":1848,"name":"Amataima-ta"},{"id":573931,"id_state":1848,"name":"Amauruc"},{"id":573942,"id_state":1848,"name":"Amurug"},{"id":573948,"id_state":1848,"name":"Anacoco"},{"id":573952,"id_state":1848,"name":"Anaricapay"},{"id":573956,"id_state":1848,"name":"Ancón"},{"id":573971,"id_state":1848,"name":"Ángel Costodio"},{"id":573972,"id_state":1848,"name":"Angel Custodio"},{"id":573978,"id_state":1848,"name":"Angostura"},{"id":573981,"id_state":1848,"name":"Angosturita"},{"id":574020,"id_state":1848,"name":"Aparurén"},{"id":574024,"id_state":1848,"name":"Apoipó"},{"id":574028,"id_state":1848,"name":"Apoypué"},{"id":574032,"id_state":1848,"name":"Apururén"},{"id":574035,"id_state":1848,"name":"Arabelo"},{"id":574036,"id_state":1848,"name":"Arabeto"},{"id":574038,"id_state":1848,"name":"Aracaicu"},{"id":574070,"id_state":1848,"name":"Araiuana-quen"},{"id":574071,"id_state":1848,"name":"Araiuma-quen"},{"id":574076,"id_state":1848,"name":"Aramaya"},{"id":574092,"id_state":1848,"name":"Arauca"},{"id":574127,"id_state":1848,"name":"Arenas"},{"id":574142,"id_state":1848,"name":"Arepital"},{"id":574164,"id_state":1848,"name":"Aripao"},{"id":574176,"id_state":1848,"name":"Arorouata"},{"id":574192,"id_state":1848,"name":"Arrozal"},{"id":574206,"id_state":1848,"name":"Asiasito"},{"id":574230,"id_state":1848,"name":"Atenas"},{"id":574232,"id_state":1848,"name":"Auarada"},{"id":574237,"id_state":1848,"name":"Aurora"},{"id":574244,"id_state":1848,"name":"Ave Chica"},{"id":574264,"id_state":1848,"name":"Aza"},{"id":574272,"id_state":1848,"name":"Bacalao"},{"id":574300,"id_state":1848,"name":"Bajo Borbón"},{"id":574337,"id_state":1848,"name":"Balchises"},{"id":574413,"id_state":1848,"name":"Barbas de Oro"},{"id":574451,"id_state":1848,"name":"Barranca"},{"id":574460,"id_state":1848,"name":"Barrancas"},{"id":574508,"id_state":1848,"name":"Barrialón"},{"id":574555,"id_state":1848,"name":"Baschi"},{"id":574591,"id_state":1848,"name":"Bejuquero"},{"id":574600,"id_state":1848,"name":"Belén"},{"id":574615,"id_state":1848,"name":"Bella Vista"},{"id":574640,"id_state":1848,"name":"Bello Monte"},{"id":574641,"id_state":1848,"name":"Bellorín"},{"id":574661,"id_state":1848,"name":"Betania"},{"id":574667,"id_state":1848,"name":"Bianchi"},{"id":574782,"id_state":1848,"name":"Boca de Marhuanta"},{"id":574790,"id_state":1848,"name":"Boca de Monte"},{"id":574805,"id_state":1848,"name":"Boca de Suapure"},{"id":574813,"id_state":1848,"name":"Boca de Tigre"},{"id":574859,"id_state":1848,"name":"Bochinche"},{"id":574887,"id_state":1848,"name":"Bolívar"},{"id":574895,"id_state":1848,"name":"Bongo"},{"id":574898,"id_state":1848,"name":"Bonitas"},{"id":574900,"id_state":1848,"name":"Bons"},{"id":574902,"id_state":1848,"name":"Boquerón"},{"id":574929,"id_state":1848,"name":"Borbón"},{"id":574964,"id_state":1848,"name":"Botamano"},{"id":574971,"id_state":1848,"name":"Botijoncito"},{"id":575013,"id_state":1848,"name":"Bucaral"},{"id":575042,"id_state":1848,"name":"Buena Esperanza"},{"id":575049,"id_state":1848,"name":"Buena Vista"},{"id":575092,"id_state":1848,"name":"Buen Pastor"},{"id":575093,"id_state":1848,"name":"Buen Retiro"},{"id":575094,"id_state":1848,"name":"Buen Vista"},{"id":575121,"id_state":1848,"name":"Caballape"},{"id":575125,"id_state":1848,"name":"Caballupe"},{"id":575134,"id_state":1848,"name":"Cabeceras de Barima"},{"id":575149,"id_state":1848,"name":"Cabeza Mala"},{"id":575156,"id_state":1848,"name":"Cabrena"},{"id":575187,"id_state":1848,"name":"Cachicamo"},{"id":575211,"id_state":1848,"name":"Cachipo"},{"id":575236,"id_state":1848,"name":"Caicara"},{"id":575239,"id_state":1848,"name":"Caicara del Orinoco"},{"id":575241,"id_state":1848,"name":"Caicara de Orinoco"},{"id":575278,"id_state":1848,"name":"Caja Negra"},{"id":575320,"id_state":1848,"name":"California"},{"id":575340,"id_state":1848,"name":"Camadacatá"},{"id":575345,"id_state":1848,"name":"Camarata"},{"id":575366,"id_state":1848,"name":"Cambur"},{"id":575399,"id_state":1848,"name":"Camoirán"},{"id":575415,"id_state":1848,"name":"Campamento del Guri"},{"id":575425,"id_state":1848,"name":"Campetoi"},{"id":575480,"id_state":1848,"name":"Campo Grande"},{"id":575524,"id_state":1848,"name":"Camuquén"},{"id":575526,"id_state":1848,"name":"Camurica"},{"id":575557,"id_state":1848,"name":"Cañafistolar"},{"id":575592,"id_state":1848,"name":"Candelaria"},{"id":575652,"id_state":1848,"name":"Caño Chiquito"},{"id":575662,"id_state":1848,"name":"Caño de Agua"},{"id":575694,"id_state":1848,"name":"Caño Hermoso"},{"id":575794,"id_state":1848,"name":"Cantina"},{"id":575795,"id_state":1848,"name":"Cantinas"},{"id":575835,"id_state":1848,"name":"Capilla Virgen del Pilar"},{"id":575850,"id_state":1848,"name":"Capuchino"},{"id":575869,"id_state":1848,"name":"Carabobo"},{"id":575898,"id_state":1848,"name":"Caramacatal"},{"id":575929,"id_state":1848,"name":"Carapo"},{"id":575931,"id_state":1848,"name":"Caraqueño"},{"id":575942,"id_state":1848,"name":"Caratal"},{"id":575951,"id_state":1848,"name":"Caratica"},{"id":575955,"id_state":1848,"name":"Carauchi"},{"id":575957,"id_state":1848,"name":"Carauren"},{"id":575988,"id_state":1848,"name":"Cardozo"},{"id":576001,"id_state":1848,"name":"Cariba"},{"id":576020,"id_state":1848,"name":"Carioca"},{"id":576021,"id_state":1848,"name":"Caripa"},{"id":576026,"id_state":1848,"name":"Caripo"},{"id":576059,"id_state":1848,"name":"Caroní"},{"id":576138,"id_state":1848,"name":"Caruach"},{"id":576139,"id_state":1848,"name":"Caruachi"},{"id":576144,"id_state":1848,"name":"Carucumerú"},{"id":576161,"id_state":1848,"name":"Carutico"},{"id":576162,"id_state":1848,"name":"Caruto"},{"id":576176,"id_state":1848,"name":"Casacoima"},{"id":576204,"id_state":1848,"name":"Casanare"},{"id":576213,"id_state":1848,"name":"Casas Viejas"},{"id":576239,"id_state":1848,"name":"Casimirito"},{"id":576252,"id_state":1848,"name":"Castillejo"},{"id":576255,"id_state":1848,"name":"Castillero"},{"id":576265,"id_state":1848,"name":"Castillo"},{"id":576355,"id_state":1848,"name":"Cavanayén"},{"id":576378,"id_state":1848,"name":"Cedeño"},{"id":576389,"id_state":1848,"name":"Ceiba"},{"id":576568,"id_state":1848,"name":"Chalana"},{"id":576640,"id_state":1848,"name":"Chiguao"},{"id":576645,"id_state":1848,"name":"Chiguire"},{"id":576662,"id_state":1848,"name":"Chinaday"},{"id":576768,"id_state":1848,"name":"Chuponal"},{"id":576813,"id_state":1848,"name":"Cintillo"},{"id":576819,"id_state":1848,"name":"Ciratobo"},{"id":576823,"id_state":1848,"name":"Ciudad Bolívar"},{"id":576827,"id_state":1848,"name":"Ciudad Guayana"},{"id":576828,"id_state":1848,"name":"Ciudad Guiana"},{"id":576830,"id_state":1848,"name":"Ciudad Piar"},{"id":576842,"id_state":1848,"name":"Clavinal"},{"id":576968,"id_state":1848,"name":"Comepoco"},{"id":576973,"id_state":1848,"name":"Comunidad"},{"id":577082,"id_state":1848,"name":"Corobal"},{"id":577101,"id_state":1848,"name":"Corocoro"},{"id":577113,"id_state":1848,"name":"Corozal"},{"id":577149,"id_state":1848,"name":"Corrales"},{"id":577254,"id_state":1848,"name":"Crucero Las Majadas"},{"id":577273,"id_state":1848,"name":"Cruzero"},{"id":577326,"id_state":1848,"name":"Cuchivero"},{"id":577327,"id_state":1848,"name":"Cuchiveros"},{"id":577329,"id_state":1848,"name":"Cucurital"},{"id":577349,"id_state":1848,"name":"Cueva del Tigre"},{"id":577395,"id_state":1848,"name":"Culebra"},{"id":577486,"id_state":1848,"name":"Curatabaca"},{"id":577496,"id_state":1848,"name":"Curi"},{"id":577500,"id_state":1848,"name":"Curiapo"},{"id":577512,"id_state":1848,"name":"Curiquima"},{"id":577600,"id_state":1848,"name":"Divina Pastora"},{"id":577636,"id_state":1848,"name":"Dos Lagunas"},{"id":577642,"id_state":1848,"name":"Duana"},{"id":577657,"id_state":1848,"name":"Egueipa"},{"id":577663,"id_state":1848,"name":"El Abismo"},{"id":577767,"id_state":1848,"name":"El Altico"},{"id":577846,"id_state":1848,"name":"El Aserradero"},{"id":577891,"id_state":1848,"name":"El Banco"},{"id":577911,"id_state":1848,"name":"El Báquiro"},{"id":578074,"id_state":1848,"name":"El Cacho"},{"id":578107,"id_state":1848,"name":"El Callao"},{"id":578110,"id_state":1848,"name":"El Callo"},{"id":578143,"id_state":1848,"name":"El Campo"},{"id":578257,"id_state":1848,"name":"El Caro"},{"id":578292,"id_state":1848,"name":"El Castellano"},{"id":578293,"id_state":1848,"name":"El Castillo"},{"id":578552,"id_state":1848,"name":"El Coco"},{"id":578637,"id_state":1848,"name":"El Corozo"},{"id":578668,"id_state":1848,"name":"El Cruce"},{"id":578742,"id_state":1848,"name":"El Danto"},{"id":578781,"id_state":1848,"name":"El Diamante"},{"id":578810,"id_state":1848,"name":"El Dorado"},{"id":578822,"id_state":1848,"name":"El Drago"},{"id":578841,"id_state":1848,"name":"El Encanto"},{"id":578858,"id_state":1848,"name":"El Entierro"},{"id":578878,"id_state":1848,"name":"El Espinero"},{"id":578941,"id_state":1848,"name":"El Gallo"},{"id":578952,"id_state":1848,"name":"El Gato"},{"id":578971,"id_state":1848,"name":"El Grillero"},{"id":579031,"id_state":1848,"name":"El Guamo"},{"id":579057,"id_state":1848,"name":"El Guarray"},{"id":579063,"id_state":1848,"name":"El Guásimo"},{"id":579117,"id_state":1848,"name":"El Hatico"},{"id":579312,"id_state":1848,"name":"El León"},{"id":579326,"id_state":1848,"name":"El Limón"},{"id":579376,"id_state":1848,"name":"El Machete"},{"id":579449,"id_state":1848,"name":"El Manteco"},{"id":579513,"id_state":1848,"name":"El Miamo"},{"id":579538,"id_state":1848,"name":"El Mirador"},{"id":579578,"id_state":1848,"name":"El Moriche"},{"id":579612,"id_state":1848,"name":"El Muerto"},{"id":579729,"id_state":1848,"name":"El Pailón"},{"id":579756,"id_state":1848,"name":"El Palmar"},{"id":579809,"id_state":1848,"name":"El Pao"},{"id":579848,"id_state":1848,"name":"El Paraíso"},{"id":579871,"id_state":1848,"name":"El Pariche"},{"id":579885,"id_state":1848,"name":"El Paso de La Fortuna"},{"id":579906,"id_state":1848,"name":"El Paují"},{"id":579990,"id_state":1848,"name":"El Perro"},{"id":579996,"id_state":1848,"name":"El Perú"},{"id":580042,"id_state":1848,"name":"El Pilón"},{"id":580116,"id_state":1848,"name":"El Portachuelo"},{"id":580214,"id_state":1848,"name":"El Puente"},{"id":580291,"id_state":1848,"name":"El Regreso"},{"id":580362,"id_state":1848,"name":"El Rincón de Turapa"},{"id":580404,"id_state":1848,"name":"El Rosario"},{"id":580418,"id_state":1848,"name":"El Rubí"},{"id":580456,"id_state":1848,"name":"El Salto"},{"id":580504,"id_state":1848,"name":"El Silencio"},{"id":580515,"id_state":1848,"name":"El Silvestre"},{"id":580639,"id_state":1848,"name":"El Tigre"},{"id":580655,"id_state":1848,"name":"El Tigre del Drago"},{"id":580861,"id_state":1848,"name":"El Ventuario"},{"id":580884,"id_state":1848,"name":"El Vigía"},{"id":580897,"id_state":1848,"name":"El Volcán"},{"id":580919,"id_state":1848,"name":"El Zamuro"},{"id":581012,"id_state":1848,"name":"España"},{"id":581020,"id_state":1848,"name":"Esperanza"},{"id":581060,"id_state":1848,"name":"Evenequén"},{"id":581110,"id_state":1848,"name":"Firinya"},{"id":581151,"id_state":1848,"name":"Fundo Valle Verde"},{"id":581211,"id_state":1848,"name":"Garcitas"},{"id":581263,"id_state":1848,"name":"Gómez"},{"id":581272,"id_state":1848,"name":"Gorro Viejo"},{"id":581286,"id_state":1848,"name":"Grimaldi"},{"id":581309,"id_state":1848,"name":"Guacara"},{"id":581379,"id_state":1848,"name":"Guaimare"},{"id":581384,"id_state":1848,"name":"Guaina"},{"id":581438,"id_state":1848,"name":"Guamure"},{"id":581443,"id_state":1848,"name":"Guaña"},{"id":581501,"id_state":1848,"name":"Guará"},{"id":581588,"id_state":1848,"name":"Guarenta"},{"id":581606,"id_state":1848,"name":"Guaricoto"},{"id":581612,"id_state":1848,"name":"Guarimba"},{"id":581682,"id_state":1848,"name":"Guasipati"},{"id":581716,"id_state":1848,"name":"Guayabal"},{"id":581772,"id_state":1848,"name":"Guayana City"},{"id":581774,"id_state":1848,"name":"Guayapo"},{"id":581775,"id_state":1848,"name":"Guayaraca"},{"id":581838,"id_state":1848,"name":"Guri"},{"id":581849,"id_state":1848,"name":"Guyabal"},{"id":581921,"id_state":1848,"name":"Hato Casa Blanca"},{"id":581949,"id_state":1848,"name":"Hato La Floresta"},{"id":582008,"id_state":1848,"name":"Higuerote"},{"id":582070,"id_state":1848,"name":"Icabarú"},{"id":582083,"id_state":1848,"name":"Ikabarú"},{"id":582103,"id_state":1848,"name":"Ipotureima"},{"id":582108,"id_state":1848,"name":"Irapa"},{"id":582354,"id_state":1848,"name":"Kamarata"},{"id":582355,"id_state":1848,"name":"Kanavayén"},{"id":582357,"id_state":1848,"name":"Kavanayén"},{"id":582393,"id_state":1848,"name":"Kilómetro Ochenta y Ocho"},{"id":582401,"id_state":1848,"name":"Kilómetro Sesenta y Siete"},{"id":582456,"id_state":1848,"name":"Kilometro 88"},{"id":582516,"id_state":1848,"name":"La Alegría"},{"id":582606,"id_state":1848,"name":"La Bandera"},{"id":582627,"id_state":1848,"name":"La Becerra"},{"id":582667,"id_state":1848,"name":"La Boca de La Pica"},{"id":582680,"id_state":1848,"name":"La Bomba"},{"id":582852,"id_state":1848,"name":"La Carata"},{"id":582875,"id_state":1848,"name":"La Carolina"},{"id":582896,"id_state":1848,"name":"La Casualidad"},{"id":582917,"id_state":1848,"name":"La Ceiba"},{"id":582941,"id_state":1848,"name":"La Ceibita"},{"id":583027,"id_state":1848,"name":"La Clarita"},{"id":583048,"id_state":1848,"name":"La Colmena"},{"id":583054,"id_state":1848,"name":"La Colonia"},{"id":583063,"id_state":1848,"name":"La Concepción"},{"id":583108,"id_state":1848,"name":"La Cordillera"},{"id":583110,"id_state":1848,"name":"La Corianera"},{"id":583146,"id_state":1848,"name":"La Cruz"},{"id":583349,"id_state":1848,"name":"La Esmeralda"},{"id":583405,"id_state":1848,"name":"La Estrella"},{"id":583414,"id_state":1848,"name":"La Fe"},{"id":583417,"id_state":1848,"name":"La Fé"},{"id":583441,"id_state":1848,"name":"La Flor"},{"id":583458,"id_state":1848,"name":"La Florida"},{"id":583543,"id_state":1848,"name":"La Gasolina"},{"id":583824,"id_state":1848,"name":"La Isabel"},{"id":583851,"id_state":1848,"name":"Laja Larga"},{"id":583855,"id_state":1848,"name":"Laja Negra"},{"id":583908,"id_state":1848,"name":"La Laja"},{"id":583919,"id_state":1848,"name":"La Lajita"},{"id":583922,"id_state":1848,"name":"La Lanta"},{"id":584011,"id_state":1848,"name":"La Lucha"},{"id":584108,"id_state":1848,"name":"La Margarita"},{"id":584134,"id_state":1848,"name":"La Mata"},{"id":584321,"id_state":1848,"name":"La Murea"},{"id":584342,"id_state":1848,"name":"La Nieve"},{"id":584416,"id_state":1848,"name":"La Palmira"},{"id":584470,"id_state":1848,"name":"La Paragua"},{"id":584600,"id_state":1848,"name":"La Piciña"},{"id":584642,"id_state":1848,"name":"La Plata"},{"id":584650,"id_state":1848,"name":"La Playa"},{"id":584662,"id_state":1848,"name":"La Playita"},{"id":584707,"id_state":1848,"name":"La Prisión"},{"id":584829,"id_state":1848,"name":"La Reforma"},{"id":584879,"id_state":1848,"name":"La Rivera"},{"id":584951,"id_state":1848,"name":"La Sabanita"},{"id":584993,"id_state":1848,"name":"La Salvación"},{"id":585000,"id_state":1848,"name":"Las Ánimas"},{"id":585017,"id_state":1848,"name":"Las Auras Viejas"},{"id":585047,"id_state":1848,"name":"Las Bombitas"},{"id":585049,"id_state":1848,"name":"Las Bonitas"},{"id":585139,"id_state":1848,"name":"Las Casitas"},{"id":585236,"id_state":1848,"name":"Las Cuevas"},{"id":585266,"id_state":1848,"name":"Las Delicias"},{"id":585324,"id_state":1848,"name":"Las Florecitas"},{"id":585340,"id_state":1848,"name":"Las Flores"},{"id":585354,"id_state":1848,"name":"Las Garzas"},{"id":585516,"id_state":1848,"name":"Las Majadas"},{"id":585545,"id_state":1848,"name":"Las Margaritas"},{"id":585549,"id_state":1848,"name":"Las Marías"},{"id":585570,"id_state":1848,"name":"Las Matas"},{"id":585585,"id_state":1848,"name":"Las Merceders"},{"id":585600,"id_state":1848,"name":"Las Mercedes"},{"id":585671,"id_state":1848,"name":"Las Nieves"},{"id":585803,"id_state":1848,"name":"Las Piedritas"},{"id":585934,"id_state":1848,"name":"Las Tejas"},{"id":585941,"id_state":1848,"name":"Las Termopilas"},{"id":586058,"id_state":1848,"name":"Las Ventanas"},{"id":586119,"id_state":1848,"name":"La Tigra"},{"id":586129,"id_state":1848,"name":"La Tigrera"},{"id":586189,"id_state":1848,"name":"La Trinidad"},{"id":586208,"id_state":1848,"name":"La Unión"},{"id":586223,"id_state":1848,"name":"La Urbana"},{"id":586326,"id_state":1848,"name":"La Victoria"},{"id":586408,"id_state":1848,"name":"La Yegüera"},{"id":586431,"id_state":1848,"name":"La Zorra"},{"id":586685,"id_state":1848,"name":"Los Apamates"},{"id":586711,"id_state":1848,"name":"Los Arrecifes"},{"id":586879,"id_state":1848,"name":"Los Caños"},{"id":586907,"id_state":1848,"name":"Los Caribes"},{"id":587011,"id_state":1848,"name":"Los Cocos"},{"id":587044,"id_state":1848,"name":"Los Corazonas"},{"id":587045,"id_state":1848,"name":"Los Corazones"},{"id":587115,"id_state":1848,"name":"Los Ermitaños"},{"id":587116,"id_state":1848,"name":"Los Españoles"},{"id":587136,"id_state":1848,"name":"Los Garzones"},{"id":587193,"id_state":1848,"name":"Los Hicoteos"},{"id":587224,"id_state":1848,"name":"Los Jabillos"},{"id":587276,"id_state":1848,"name":"Los Linderos"},{"id":587285,"id_state":1848,"name":"Los Llopitos"},{"id":587317,"id_state":1848,"name":"Los Mangos"},{"id":587321,"id_state":1848,"name":"Los Manguitos"},{"id":587387,"id_state":1848,"name":"Los Moriches"},{"id":587481,"id_state":1848,"name":"Los Pasotes"},{"id":587514,"id_state":1848,"name":"Los Pijiguaos"},{"id":587515,"id_state":1848,"name":"Los Pijiguigados"},{"id":587535,"id_state":1848,"name":"Los Placeres"},{"id":587648,"id_state":1848,"name":"Los Robles"},{"id":587777,"id_state":1848,"name":"Luepa"},{"id":587780,"id_state":1848,"name":"Luoromota"},{"id":587919,"id_state":1848,"name":"Maiparú"},{"id":587923,"id_state":1848,"name":"Maipure"},{"id":587983,"id_state":1848,"name":"Mamonal"},{"id":588038,"id_state":1848,"name":"Manganeso"},{"id":588076,"id_state":1848,"name":"Manirotal"},{"id":588095,"id_state":1848,"name":"Manteco"},{"id":588097,"id_state":1848,"name":"Mantecote"},{"id":588218,"id_state":1848,"name":"Margarita"},{"id":588221,"id_state":1848,"name":"Marhuanta"},{"id":588228,"id_state":1848,"name":"María Luisa"},{"id":588253,"id_state":1848,"name":"Maripa"},{"id":588321,"id_state":1848,"name":"Mata de Agua"},{"id":588344,"id_state":1848,"name":"Mata de Corocito"},{"id":588346,"id_state":1848,"name":"Mata de Cuchillo"},{"id":588420,"id_state":1848,"name":"Matahambre"},{"id":588445,"id_state":1848,"name":"Matanza"},{"id":588446,"id_state":1848,"name":"Matanzas"},{"id":588462,"id_state":1848,"name":"Matapalo"},{"id":588509,"id_state":1848,"name":"Matu"},{"id":588541,"id_state":1848,"name":"Mayor"},{"id":588543,"id_state":1848,"name":"Mayorí"},{"id":588546,"id_state":1848,"name":"Mayupa"},{"id":588605,"id_state":1848,"name":"Mercedes"},{"id":588608,"id_state":1848,"name":"Merecural"},{"id":588637,"id_state":1848,"name":"Merey"},{"id":588640,"id_state":1848,"name":"Mereyal"},{"id":588741,"id_state":1848,"name":"Mina del Pao"},{"id":588761,"id_state":1848,"name":"Miraflores"},{"id":588814,"id_state":1848,"name":"Mochila"},{"id":588839,"id_state":1848,"name":"Moitaco"},{"id":588866,"id_state":1848,"name":"Moncerrat"},{"id":588992,"id_state":1848,"name":"Morichalito"},{"id":589001,"id_state":1848,"name":"Morichal Verde"},{"id":589005,"id_state":1848,"name":"Moriche"},{"id":589170,"id_state":1848,"name":"Mundo Nuevo"},{"id":589203,"id_state":1848,"name":"Nacupay"},{"id":589249,"id_state":1848,"name":"Nieves"},{"id":589291,"id_state":1848,"name":"Nuevo Mundo"},{"id":589305,"id_state":1848,"name":"Ochi"},{"id":589423,"id_state":1848,"name":"Orinoquito"},{"id":589430,"id_state":1848,"name":"Orocopiche"},{"id":589510,"id_state":1848,"name":"Pajal"},{"id":589547,"id_state":1848,"name":"Palau"},{"id":589596,"id_state":1848,"name":"Palmarita"},{"id":589606,"id_state":1848,"name":"Palmarito"},{"id":589694,"id_state":1848,"name":"Palo Grande"},{"id":589734,"id_state":1848,"name":"Palúa"},{"id":589746,"id_state":1848,"name":"Panadero"},{"id":589766,"id_state":1848,"name":"Pan de Azúcar"},{"id":589792,"id_state":1848,"name":"Papelón"},{"id":589843,"id_state":1848,"name":"Parai-tepuí"},{"id":589892,"id_state":1848,"name":"Paraytepuy"},{"id":589901,"id_state":1848,"name":"Parguaza"},{"id":589917,"id_state":1848,"name":"Parupa"},{"id":590036,"id_state":1848,"name":"Pastora"},{"id":590063,"id_state":1848,"name":"Patrero Alemán"},{"id":590203,"id_state":1848,"name":"Perai-tepuí"},{"id":590242,"id_state":1848,"name":"Perú"},{"id":590313,"id_state":1848,"name":"Piedra de Buena Vista"},{"id":590372,"id_state":1848,"name":"Pijiguao"},{"id":590383,"id_state":1848,"name":"Piloncito"},{"id":590387,"id_state":1848,"name":"Piña"},{"id":590485,"id_state":1848,"name":"Playa Blanca"},{"id":590525,"id_state":1848,"name":"Plomo"},{"id":590615,"id_state":1848,"name":"Potrero"},{"id":590659,"id_state":1848,"name":"Pozo Hondo"},{"id":590676,"id_state":1848,"name":"Prado"},{"id":590678,"id_state":1848,"name":"Praitepuy"},{"id":590697,"id_state":1848,"name":"Puchilito"},{"id":590701,"id_state":1848,"name":"Pueblito"},{"id":590746,"id_state":1848,"name":"Pueblo Viejo de Altagracia"},{"id":590763,"id_state":1848,"name":"Puente Maniapure"},{"id":590800,"id_state":1848,"name":"Puerto"},{"id":590804,"id_state":1848,"name":"Puerto Aricagua"},{"id":590816,"id_state":1848,"name":"Puerto Cabello del Caura"},{"id":590836,"id_state":1848,"name":"Puerto de Las Botellas"},{"id":590842,"id_state":1848,"name":"Puerto de Ordaz"},{"id":590855,"id_state":1848,"name":"Puerto Escondido"},{"id":590865,"id_state":1848,"name":"Puerto Hormigo"},{"id":590884,"id_state":1848,"name":"Puerto Miranda"},{"id":590897,"id_state":1848,"name":"Puerto Ordaz"},{"id":590909,"id_state":1848,"name":"Puerto Rico"},{"id":590926,"id_state":1848,"name":"Puerto Tablas"},{"id":590927,"id_state":1848,"name":"Puerto Tapaquire"},{"id":590966,"id_state":1848,"name":"Punta de Laja"},{"id":590988,"id_state":1848,"name":"Punta Miranda"},{"id":590991,"id_state":1848,"name":"Punta Nueva"},{"id":590996,"id_state":1848,"name":"Punto de Vista"},{"id":591009,"id_state":1848,"name":"Purgatorio"},{"id":591137,"id_state":1848,"name":"Quesera El Potrero"},{"id":591160,"id_state":1848,"name":"Quino"},{"id":591249,"id_state":1848,"name":"Rancho Caroni"},{"id":591305,"id_state":1848,"name":"Reforma"},{"id":591364,"id_state":1848,"name":"Rincón Bonito"},{"id":591439,"id_state":1848,"name":"Río Claro"},{"id":591578,"id_state":1848,"name":"Sabana"},{"id":591625,"id_state":1848,"name":"Sabana Grande"},{"id":591665,"id_state":1848,"name":"Sabaneta"},{"id":591691,"id_state":1848,"name":"Sabanetica"},{"id":591709,"id_state":1848,"name":"Sacuima"},{"id":591734,"id_state":1848,"name":"Salazal"},{"id":591767,"id_state":1848,"name":"Salva la Patria"},{"id":591804,"id_state":1848,"name":"San Andrés"},{"id":591898,"id_state":1848,"name":"San Cayetano"},{"id":591909,"id_state":1848,"name":"San Cristobal"},{"id":591936,"id_state":1848,"name":"San Feliciano"},{"id":591951,"id_state":1848,"name":"San Felis"},{"id":591957,"id_state":1848,"name":"San Félix"},{"id":591959,"id_state":1848,"name":"San Félix de Guayana"},{"id":591971,"id_state":1848,"name":"San Francisco"},{"id":591997,"id_state":1848,"name":"San Germán"},{"id":592022,"id_state":1848,"name":"San Isidro"},{"id":592079,"id_state":1848,"name":"San José"},{"id":592211,"id_state":1848,"name":"San Lorenzo"},{"id":592259,"id_state":1848,"name":"San Martín de Turumban"},{"id":592269,"id_state":1848,"name":"San Miguel"},{"id":592311,"id_state":1848,"name":"San Pablo"},{"id":592359,"id_state":1848,"name":"San Pedro de Las Bocas"},{"id":592366,"id_state":1848,"name":"San Rafael"},{"id":592392,"id_state":1848,"name":"San Rafael de Imataca"},{"id":592423,"id_state":1848,"name":"San Roque"},{"id":592424,"id_state":1848,"name":"San Salvador"},{"id":592443,"id_state":1848,"name":"Santa Ana"},{"id":592469,"id_state":1848,"name":"Santa Barbara"},{"id":592476,"id_state":1848,"name":"Santa Bárbara"},{"id":592514,"id_state":1848,"name":"Santa Cruz"},{"id":592550,"id_state":1848,"name":"Santa Elena"},{"id":592564,"id_state":1848,"name":"Santa Elena de Guairén"},{"id":592566,"id_state":1848,"name":"Santa Elena de Uairén"},{"id":592581,"id_state":1848,"name":"Santa Fé"},{"id":592607,"id_state":1848,"name":"Santa Isabel"},{"id":592646,"id_state":1848,"name":"Santa María"},{"id":592669,"id_state":1848,"name":"Santa Marta"},{"id":592689,"id_state":1848,"name":"Santa Rita"},{"id":592710,"id_state":1848,"name":"Santa Rosa"},{"id":592746,"id_state":1848,"name":"Santa Rosalía"},{"id":592755,"id_state":1848,"name":"Santa Teresa"},{"id":592775,"id_state":1848,"name":"Santo Domingo"},{"id":592795,"id_state":1848,"name":"San Tomé de Guayana"},{"id":592798,"id_state":1848,"name":"Santo Tomas"},{"id":592801,"id_state":1848,"name":"Santo Tomé de Guayana"},{"id":592814,"id_state":1848,"name":"San Vicente"},{"id":592865,"id_state":1848,"name":"Seccion San Felix"},{"id":592872,"id_state":1848,"name":"Sejal"},{"id":592930,"id_state":1848,"name":"Sinforero"},{"id":592949,"id_state":1848,"name":"Sitio La Rosa"},{"id":592975,"id_state":1848,"name":"Soledad"},{"id":592997,"id_state":1848,"name":"Sonora"},{"id":593018,"id_state":1848,"name":"Sua Sua"},{"id":593030,"id_state":1848,"name":"Sucutun"},{"id":593035,"id_state":1848,"name":"Sumua-parú-mata"},{"id":593040,"id_state":1848,"name":"Surama"},{"id":593101,"id_state":1848,"name":"Tagroima"},{"id":593232,"id_state":1848,"name":"Temblador"},{"id":593244,"id_state":1848,"name":"Tente Duro"},{"id":593250,"id_state":1848,"name":"Terecay"},{"id":593254,"id_state":1848,"name":"Caño Terecay"},{"id":593367,"id_state":1848,"name":"Tocoma"},{"id":593389,"id_state":1848,"name":"Tokio"},{"id":593482,"id_state":1848,"name":"Trapichote"},{"id":593504,"id_state":1848,"name":"Tres Piedras"},{"id":593505,"id_state":1848,"name":"Triana"},{"id":593540,"id_state":1848,"name":"Tshuau"},{"id":593593,"id_state":1848,"name":"Tumeremo"},{"id":593634,"id_state":1848,"name":"Túriba"},{"id":593656,"id_state":1848,"name":"Tzhuau"},{"id":593658,"id_state":1848,"name":"Uadaparú"},{"id":593664,"id_state":1848,"name":"Uarapata"},{"id":593675,"id_state":1848,"name":"Uiruma-ta"},{"id":593676,"id_state":1848,"name":"Uiruma-tá"},{"id":593690,"id_state":1848,"name":"Uonquén"},{"id":593691,"id_state":1848,"name":"Upata"},{"id":593698,"id_state":1848,"name":"Uradai"},{"id":593699,"id_state":1848,"name":"Uraday"},{"id":593710,"id_state":1848,"name":"Urbana"},{"id":593784,"id_state":1848,"name":"Urimán"},{"id":593785,"id_state":1848,"name":"Urimba-ta"},{"id":593806,"id_state":1848,"name":"Uruyén"},{"id":593835,"id_state":1848,"name":"Vainas"},{"id":593836,"id_state":1848,"name":"Vainillal"},{"id":593846,"id_state":1848,"name":"Valencia"},{"id":593851,"id_state":1848,"name":"Valle"},{"id":593997,"id_state":1848,"name":"Victoria"},{"id":594026,"id_state":1848,"name":"Villa Flor"},{"id":594029,"id_state":1848,"name":"Villa Gladis"},{"id":594032,"id_state":1848,"name":"Villa Lola"},{"id":594046,"id_state":1848,"name":"Villa Rica"},{"id":594061,"id_state":1848,"name":"Viloria"},{"id":594151,"id_state":1848,"name":"Yaguera"},{"id":594170,"id_state":1848,"name":"Yberia"},{"id":594177,"id_state":1848,"name":"Yerichaña"},{"id":594185,"id_state":1848,"name":"Yori"},{"id":594195,"id_state":1848,"name":"Yumena"},{"id":594196,"id_state":1848,"name":"Yuoromota"},{"id":594212,"id_state":1848,"name":"Zamuro"},{"id":594230,"id_state":1848,"name":"Zanjonote"},{"id":594232,"id_state":1848,"name":"Zapata"},{"id":594234,"id_state":1848,"name":"Zapateral"},{"id":594253,"id_state":1848,"name":"Zua-Zua"}]
