[{"id":444061,"id_state":1685,"name":"Achiotes"},{"id":444063,"id_state":1685,"name":"Achiotes Jumay"},{"id":444097,"id_state":1685,"name":"Aguacate"},{"id":444115,"id_state":1685,"name":"Aguamecate"},{"id":444121,"id_state":1685,"name":"Agua Tibia"},{"id":444128,"id_state":1685,"name":"Agua Zarca"},{"id":444152,"id_state":1685,"name":"Alvarado"},{"id":444291,"id_state":1685,"name":"Barrios"},{"id":444368,"id_state":1685,"name":"Buena Vista"},{"id":444540,"id_state":1685,"name":"Canton Barrios"},{"id":444748,"id_state":1685,"name":"Chaparrón"},{"id":445540,"id_state":1685,"name":"El Arenal"},{"id":445763,"id_state":1685,"name":"El Durazno"},{"id":445959,"id_state":1685,"name":"El Norte"},{"id":446026,"id_state":1685,"name":"El Pedernal"},{"id":446770,"id_state":1685,"name":"Jalapa"},{"id":446796,"id_state":1685,"name":"Jilotepeque"},{"id":446904,"id_state":1685,"name":"La Aurora"},{"id":446941,"id_state":1685,"name":"La Campana"},{"id":447853,"id_state":1685,"name":"Los Olivos"},{"id":448039,"id_state":1685,"name":"Mataquescuintla"},{"id":448040,"id_state":1685,"name":"Mataquesquintla"},{"id":448111,"id_state":1685,"name":"Monjas"},{"id":448733,"id_state":1685,"name":"Piedras Negras"},{"id":449625,"id_state":1685,"name":"San Luis Jilotepeque"},{"id":449727,"id_state":1685,"name":"San Pedro Pinula"},{"id":450360,"id_state":1685,"name":"Tatasirire"}]
