[{"id":67815,"id_state":730,"name":"Bilten"},{"id":67816,"id_state":730,"name":"Braunwald"},{"id":67817,"id_state":730,"name":"Elm"},{"id":67818,"id_state":730,"name":"Engi"},{"id":67819,"id_state":730,"name":"Ennenda"},{"id":67820,"id_state":730,"name":"Filzbach"},{"id":67821,"id_state":730,"name":"Glarus"},{"id":67822,"id_state":730,"name":"H채tzingen"},{"id":67824,"id_state":730,"name":"Leuggelbach"},{"id":67826,"id_state":730,"name":"Luchsingen"},{"id":67828,"id_state":730,"name":"Mollis"},{"id":67829,"id_state":730,"name":"M체hlehorn"},{"id":67830,"id_state":730,"name":"N채fels"},{"id":67831,"id_state":730,"name":"Netstal"},{"id":67833,"id_state":730,"name":"Niederurnen"},{"id":67835,"id_state":730,"name":"Riedern"},{"id":67837,"id_state":730,"name":"Ziegelbr체cke"}]
