[{"id":268780,"id_state":1039,"name":"Bakici"},{"id":268803,"id_state":1039,"name":"Baletine"},{"id":268819,"id_state":1039,"name":"Bani"},{"id":268873,"id_state":1039,"name":"Bare"},{"id":269345,"id_state":1039,"name":"Bosanka"},{"id":269877,"id_state":1039,"name":"Cavtat"},{"id":270029,"id_state":1039,"name":"Cilipi"},{"id":271040,"id_state":1039,"name":"Dubrovnik"},{"id":271041,"id_state":1039,"name":"Dubrovnik II"},{"id":271985,"id_state":1039,"name":"Gruz"},{"id":272934,"id_state":1039,"name":"Kolocep"},{"id":273447,"id_state":1039,"name":"Kuna"},{"id":273871,"id_state":1039,"name":"Lovorno"},{"id":274712,"id_state":1039,"name":"Mokosica"},{"id":275511,"id_state":1039,"name":"Pavlje Brdo"}]
