[{"id":2018,"id_country":27,"name":"Dublin"},{"id":2019,"id_country":27,"name":"Galway"},{"id":2020,"id_country":27,"name":"Kildare"},{"id":2021,"id_country":27,"name":"Leitrim"},{"id":2022,"id_country":27,"name":"Limerick"},{"id":2023,"id_country":27,"name":"Mayo"},{"id":2024,"id_country":27,"name":"Meath"},{"id":2025,"id_country":27,"name":"Carlow"},{"id":2026,"id_country":27,"name":"Kilkenny"},{"id":2027,"id_country":27,"name":"Laois"},{"id":2028,"id_country":27,"name":"Longford"},{"id":2029,"id_country":27,"name":"Louth"},{"id":2030,"id_country":27,"name":"Offaly"},{"id":2031,"id_country":27,"name":"Westmeath"},{"id":2032,"id_country":27,"name":"Wexford"},{"id":2033,"id_country":27,"name":"Wicklow"},{"id":2034,"id_country":27,"name":"Roscommon"},{"id":2035,"id_country":27,"name":"Sligo"},{"id":2036,"id_country":27,"name":"Clare"},{"id":2037,"id_country":27,"name":"Cork"},{"id":2038,"id_country":27,"name":"Kerry"},{"id":2039,"id_country":27,"name":"Tipperary"},{"id":2040,"id_country":27,"name":"Waterford"},{"id":2041,"id_country":27,"name":"Cavan"},{"id":2042,"id_country":27,"name":"Donegal"},{"id":2043,"id_country":27,"name":"Monaghan"}]
